<?xml version="1.0" encoding="UTF-8"?>
<definition tile_type="2">
	<meshes>
		<mesh id="mesh0" file_name="nso_mod/meshes/mainland/6_8_main.mesh">
			<transform/>
		</mesh>
		<mesh id="StaticObject_7" file_name="nso_mod/meshes/decoration/wall_straight_long.mesh">
			<transform 00="0.984225" 02="0.176922" 20="-0.176922" 22="0.984225" 30="-387.0078" 31="24.410406" 32="134.797852"/>
		</mesh>
		<mesh id="StaticObject_6" file_name="nso_mod/meshes/decoration/wall_straight_short.mesh">
			<transform 00="0.997364" 02="-0.072558" 20="0.072558" 22="0.997364" 30="-422.584473" 31="24.242327" 32="137.379883"/>
		</mesh>
		<mesh id="StaticObject_5" file_name="nso_mod/meshes/rocks/rock_small_4.mesh">
			<transform 30="-412.745117" 31="23.972338" 32="132.749023"/>
		</mesh>
		<mesh id="StaticObject_4" file_name="nso_mod/meshes/rocks/rock_big_2.mesh">
			<transform 30="-431.218262" 31="24.818054" 32="132.459961"/>
		</mesh>
		<mesh id="StaticObject_3" file_name="nso_mod/meshes/rocks/rock_small_4.mesh">
			<transform 30="-430.736328" 31="24.09979" 32="137.567383"/>
		</mesh>
		<mesh id="StaticObject_2" file_name="nso_mod/meshes/rocks/rock_big_2.mesh">
			<transform 00="0.279244" 01="0" 02="0.96022" 10="-0.839348" 11="0.48571" 12="0.244093" 20="-0.466389" 21="-0.87412" 22="0.135632" 30="-373.553223" 31="27.059565" 32="130.685547"/>
		</mesh>
		<mesh id="StaticObject_1" file_name="nso_mod/meshes/rocks/rock_big_4.mesh">
			<transform 00="0.910995" 02="0.412418" 20="-0.412418" 22="0.910995" 30="-372.414063" 31="25.98334" 32="127.128906"/>
		</mesh>
		<mesh id="StaticObject_0" file_name="nso_mod/meshes/rocks/rock_small_2.mesh">
			<transform 11="-0.104047" 12="0.994572" 21="-0.994572" 22="-0.104047" 30="-373.9834" 31="24.85809" 32="132.2539"/>
		</mesh>
	</meshes>
	<physics_objects/>
	<physics_meshes>
		<physics_mesh id="StaticObject_7_phys" file_name="meshes/generated_object_geom/tiles/mega_island_6_8/nso_mod/decoration/wall_straight_long__StaticObject_7_phys.phys">
			<transform 00="0.984225" 02="0.176922" 20="-0.176922" 22="0.984225" 30="-387.0078" 31="24.410406" 32="134.797852"/>
		</physics_mesh>
		<physics_mesh id="StaticObject_6_phys" file_name="meshes/generated_object_geom/tiles/mega_island_6_8/nso_mod/decoration/wall_straight_short__StaticObject_6_phys.phys">
			<transform 00="0.997364" 02="-0.072558" 20="0.072558" 22="0.997364" 30="-422.584473" 31="24.242327" 32="137.379883"/>
		</physics_mesh>
		<physics_mesh id="StaticObject_5_phys" file_name="nso_mod/meshes/rocks/rock_small_4.phys">
			<transform 30="-412.745117" 31="23.972338" 32="132.749023"/>
		</physics_mesh>
		<physics_mesh id="StaticObject_4_phys" file_name="nso_mod/meshes/rocks/rock_big_2.phys">
			<transform 30="-431.218262" 31="24.818054" 32="132.459961"/>
		</physics_mesh>
		<physics_mesh id="StaticObject_3_phys" file_name="nso_mod/meshes/rocks/rock_small_4.phys">
			<transform 30="-430.736328" 31="24.09979" 32="137.567383"/>
		</physics_mesh>
		<physics_mesh id="StaticObject_2_phys" file_name="nso_mod/meshes/rocks/rock_big_2.phys">
			<transform 00="0.279244" 01="0" 02="0.96022" 10="-0.839348" 11="0.48571" 12="0.244093" 20="-0.466389" 21="-0.87412" 22="0.135632" 30="-373.553223" 31="27.059565" 32="130.685547"/>
		</physics_mesh>
		<physics_mesh id="physics_mesh0" file_name="nso_mod/meshes/mainland/6_8_main.phys">
			<transform/>
		</physics_mesh>
		<physics_mesh id="StaticObject_1_phys" file_name="nso_mod/meshes/rocks/rock_big_4.phys">
			<transform 00="0.910995" 02="0.412418" 20="-0.412418" 22="0.910995" 30="-372.414063" 31="25.98334" 32="127.128906"/>
		</physics_mesh>
		<physics_mesh id="StaticObject_0_phys" file_name="nso_mod/meshes/rocks/rock_small_2.phys">
			<transform 11="-0.104047" 12="0.994572" 21="-0.994572" 22="-0.104047" 30="-373.9834" 31="24.85809" 32="132.2539"/>
		</physics_mesh>
	</physics_meshes>
	<physics_dynamics/>
	<lights_omni/>
	<lights_spot/>
	<lights_tube/>
	<screens/>
	<edit_areas/>
	<interactables/>
	<door_logic_nodes/>
	<light_logic_nodes/>
	<rotation_logic_nodes/>
	<hangar_door_logic_nodes/>
	<audio_logic_nodes/>
	<tile_markers/>
	<mission_zones/>
	<dynamic_markers/>
	<ladders/>
	<perches/>
	<fires/>
	<train_tracks/>
	<volcano_markers/>
	<mineral_rocks/>
</definition>

