<?xml version="1.0" encoding="UTF-8"?>
<Trees>
	<T>
		<p x="6.634766" y="13.489429" z="-295.742188" w="1.001023"/>
	</T>
	<T>
		<p x="11.642578" y="13.005147" z="-309.195313" w="0.92908"/>
	</T>
	<T>
		<p x="75.672852" y="7.564671" z="-376.408203" w="1.071251"/>
	</T>
	<T>
		<p x="82.15332" y="9.570942" z="-367.652344" w="1.078748"/>
	</T>
	<T>
		<p x="84.226563" y="10.099955" z="-375.154297" w="0.995737"/>
	</T>
	<T>
		<p x="68.887695" y="6.536484" z="-364.180664" w="1.033265"/>
	</T>
	<T>
		<p x="73.003906" y="7.517053" z="-370.213867" w="1.08403"/>
	</T>
	<T>
		<p x="92.500977" y="11.837278" z="-357.540039" w="0.965721"/>
	</T>
	<T>
		<p x="82.148438" y="9.487081" z="-357.12207" w="1.059942"/>
	</T>
	<T>
		<p x="92.324219" y="11.912354" z="-372.18457" w="1.064934"/>
	</T>
	<T>
		<p x="89.446289" y="11.056579" z="-346.352539" w="0.973865"/>
	</T>
	<T>
		<p x="-133.574219" y="1.573167" z="-493.34082" w="1.005627"/>
	</T>
	<T>
		<p x="10.606445" y="12.856956" z="-452.589844" w="1.094166"/>
	</T>
	<T>
		<p x="9.095703" y="13.992954" z="-491.521484" w="1.055902"/>
	</T>
	<T>
		<p x="32.577148" y="13.294969" z="-495.371094" w="1.099301"/>
	</T>
	<T>
		<p x="39.234375" y="13.225647" z="-483.836914" w="0.939529"/>
	</T>
	<T>
		<p x="16.717773" y="14.569204" z="-497.333984" w="0.940698"/>
	</T>
	<T>
		<p x="48.570313" y="12.102211" z="-488.329102" w="1.004663"/>
	</T>
	<T>
		<p x="-81.871094" y="12.548075" z="-487.239258" w="0.939543"/>
	</T>
	<T>
		<p x="-72.032227" y="12.560667" z="-498.921875" w="0.933157"/>
	</T>
	<T>
		<p x="-91.52832" y="12.68638" z="-496.470703" w="1.064934"/>
	</T>
	<T>
		<p x="-82.188477" y="12.485741" z="-478.354492" w="0.921528"/>
	</T>
	<T>
		<p x="-75.415039" y="12.877771" z="-464.316406" w="1.074482"/>
	</T>
	<T>
		<p x="-73.280273" y="12.478175" z="-486.326172" w="0.904416"/>
	</T>
	<T>
		<p x="-60.488281" y="12.319187" z="-481.829102" w="1.042177"/>
	</T>
	<T>
		<p x="-56.491211" y="12.02064" z="-472.477539" w="1.029756"/>
	</T>
	<T>
		<p x="-54.90332" y="12.439411" z="-454.499023" w="1.099165"/>
	</T>
	<T>
		<p x="-72.494141" y="12.392582" z="-472.234375" w="0.923186"/>
	</T>
	<T>
		<p x="-50.239258" y="12.529327" z="-423.789063" w="1.013705"/>
	</T>
	<T>
		<p x="-66.007813" y="12.531687" z="-466.863281" w="1.044721"/>
	</T>
	<T>
		<p x="-66.442383" y="12.466271" z="-491.607422" w="1.094424"/>
	</T>
	<T>
		<p x="-157.397461" y="0.154928" z="-467.638672" w="1.043022"/>
	</T>
	<T>
		<p x="-151.097656" y="0.882045" z="-483.125" w="0.968169"/>
	</T>
	<T>
		<p x="-124.46875" y="1.58626" z="-488.258789" w="0.97241"/>
	</T>
	<T>
		<p x="-136.875" y="1.159821" z="-483.363281" w="0.969194"/>
	</T>
	<T>
		<p x="-135.698242" y="0.645955" z="-475.771484" w="0.901264"/>
	</T>
	<T>
		<p x="-168.098633" y="0.154573" z="-472.772461" w="0.976608"/>
	</T>
	<T>
		<p x="-172.65918" y="1.081864" z="-494.359375" w="1.038401"/>
	</T>
	<T>
		<p x="-148.857422" y="0.616502" z="-475.288086" w="1.00338"/>
	</T>
	<T>
		<p x="-146.518555" y="0.410572" z="-468.919922" w="1.023482"/>
	</T>
	<T>
		<p x="-170.613281" y="0.729022" z="-490.087891" w="1.06014"/>
	</T>
	<T>
		<p x="-161.46582" y="0.912253" z="-490.06543" w="0.941096"/>
	</T>
	<T>
		<p x="-144.130859" y="1.190067" z="-487.751953" w="1.016896"/>
	</T>
	<T>
		<p x="-151.585938" y="1.361314" z="-498.256836" w="0.931379"/>
	</T>
	<T>
		<p x="31.975586" y="13.616302" z="-456.787109" w="0.931168"/>
	</T>
	<T>
		<p x="56.385742" y="11.125355" z="-492.630859" w="1.000188"/>
	</T>
	<T>
		<p x="46.536133" y="11.960896" z="-493.638672" w="0.961194"/>
	</T>
	<T>
		<p x="24.901367" y="14.280885" z="-491.237305" w="0.942331"/>
	</T>
	<T>
		<p x="26.308594" y="14.485535" z="-480.852539" w="1.00229"/>
	</T>
	<T>
		<p x="0.283203" y="14.1506" z="-499.945313" w="0.960111"/>
	</T>
	<T>
		<p x="0.251953" y="13.257711" z="-483.018555" w="1.091454"/>
	</T>
	<T>
		<p x="57.990234" y="12.269835" z="-465.451172" w="0.981427"/>
	</T>
	<T>
		<p x="48.883789" y="13.90899" z="-450.681641" w="0.974018"/>
	</T>
	<T>
		<p x="53.811523" y="13.14447" z="-443.555664" w="0.947079"/>
	</T>
	<T>
		<p x="39.700195" y="14.523221" z="-436.267578" w="1.065629"/>
	</T>
	<T>
		<p x="44.946289" y="13.469292" z="-425.835938" w="0.935188"/>
	</T>
	<T>
		<p x="46.110352" y="13.972895" z="-439.479492" w="1.01712"/>
	</T>
	<T>
		<p x="39.289063" y="14.254524" z="-447.90918" w="1.072222"/>
	</T>
	<T>
		<p x="41.416016" y="13.704065" z="-457.569336" w="1.086771"/>
	</T>
	<T>
		<p x="46.265625" y="13.588701" z="-466.390625" w="1.091035"/>
	</T>
	<T>
		<p x="39.52832" y="14.150398" z="-468.111328" w="1.018831"/>
	</T>
	<T>
		<p x="31.828125" y="14.293925" z="-472.394531" w="0.963042"/>
	</T>
	<T>
		<p x="64.884766" y="11.168488" z="-471.999023" w="1.071476"/>
	</T>
	<T>
		<p x="55.717773" y="13.094662" z="-458.914063" w="0.959157"/>
	</T>
	<T>
		<p x="41.789063" y="11.120636" z="-269.461914" w="1.093524"/>
	</T>
	<T>
		<p x="34.951172" y="10.931605" z="-267.319336" w="0.957876"/>
	</T>
	<T>
		<p x="35.855469" y="12.622435" z="-281.155273" w="1.024479"/>
	</T>
	<T>
		<p x="34.780273" y="11.850219" z="-273.902344" w="0.932189"/>
	</T>
	<T>
		<p x="41.789063" y="12.16599" z="-279.90625" w="1.007768"/>
	</T>
	<T>
		<p x="41.867188" y="12.420622" z="-288.834961" w="1.83401"/>
	</T>
	<T>
		<p x="40.089844" y="11.994693" z="-304.535156" w="0.978953"/>
	</T>
	<T>
		<p x="44.071289" y="11.107594" z="-314.848633" w="0.978165"/>
	</T>
	<T>
		<p x="36.873047" y="11.73662" z="-322.979492" w="0.937302"/>
	</T>
	<T>
		<p x="29.256836" y="11.847286" z="-338.554688" w="1.07392"/>
	</T>
	<T>
		<p x="31.18457" y="12.040251" z="-324.443359" w="1.069076"/>
	</T>
	<T>
		<p x="32.913086" y="12.147621" z="-314.810547" w="0.989939"/>
	</T>
	<T>
		<p x="39.15332" y="11.753496" z="-316.015625" w="0.918577"/>
	</T>
	<T>
		<p x="34.056641" y="12.17454" z="-302.254883" w="1.086468"/>
	</T>
	<T>
		<p x="34.339844" y="12.398203" z="-293.677734" w="1.004755"/>
	</T>
	<T>
		<p x="41.518555" y="12.215506" z="-296.826172" w="0.918168"/>
	</T>
	<T>
		<p x="33.904297" y="11.736671" z="-331.03418" w="1.041147"/>
	</T>
	<T>
		<p x="32.444336" y="12.549957" z="-286.459961" w="1.044067"/>
	</T>
	<T>
		<p x="34.710938" y="12.049381" z="-308.594727" w="1.025512"/>
	</T>
	<T>
		<p x="12.345703" y="13.782623" z="-270.148438" w="0.900333"/>
	</T>
	<T>
		<p x="9.055664" y="13.786203" z="-279.030273" w="1.052564"/>
	</T>
	<T>
		<p x="5.913086" y="13.643339" z="-288.566406" w="1.00122"/>
	</T>
	<T>
		<p x="14.620117" y="13.566271" z="-275.005859" w="0.94026"/>
	</T>
	<T>
		<p x="12.880859" y="13.400066" z="-287.032227" w="1.062422"/>
	</T>
	<T>
		<p x="2.803711" y="13.47574" z="-298.920898" w="1.086101"/>
	</T>
	<T>
		<p x="8.833008" y="13.147531" z="-303.112305" w="0.977182"/>
	</T>
	<T>
		<p x="13.419922" y="13.14623" z="-295.649414" w="1.073781"/>
	</T>
	<T>
		<p x="1.194336" y="13.292086" z="-307.675781" w="1.020218"/>
	</T>
	<T>
		<p x="4.006836" y="13.063929" z="-318.494141" w="1.060384"/>
	</T>
	<T>
		<p x="-11.104492" y="12.968462" z="-337.880859" w="1.094224"/>
	</T>
	<T>
		<p x="-4.237305" y="13.19548" z="-323.166016" w="1.007907"/>
	</T>
	<T>
		<p x="0.740234" y="13.051537" z="-332.334961" w="1.04608"/>
	</T>
	<T>
		<p x="8.37793" y="12.98577" z="-323.453125" w="0.948457"/>
	</T>
	<T>
		<p x="11.62207" y="12.939718" z="-316.555664" w="1.036628"/>
	</T>
	<T>
		<p x="8.652344" y="12.960905" z="-331.509766" w="1.072638"/>
	</T>
	<T>
		<p x="3.301758" y="12.813084" z="-341.962891" w="1.022893"/>
	</T>
	<T>
		<p x="-2.806641" y="12.769051" z="-343.532227" w="1.010038"/>
	</T>
	<T>
		<p x="-4.181641" y="12.531292" z="-354.301758" w="0.919026"/>
	</T>
	<T>
		<p x="2.220703" y="12.598197" z="-352.890625" w="1.026722"/>
	</T>
	<T>
		<p x="2.637695" y="12.636313" z="-364.524414" w="1.05772"/>
	</T>
	<T>
		<p x="-1.111328" y="12.613107" z="-375.078125" w="1.002692"/>
	</T>
	<T>
		<p x="-12.852539" y="12.492798" z="-375.927734" w="1.056982"/>
	</T>
	<T>
		<p x="-4.058594" y="12.547869" z="-366.03125" w="0.93581"/>
	</T>
	<T>
		<p x="-5.910156" y="12.51409" z="-362.054688" w="1.061874"/>
	</T>
	<T>
		<p x="-17.500977" y="12.529352" z="-366.870117" w="1.026826"/>
	</T>
	<T>
		<p x="-11.666016" y="12.503766" z="-370.911133" w="1.041088"/>
	</T>
	<T>
		<p x="-14.249023" y="12.644192" z="-354.056641" w="0.954205"/>
	</T>
	<T>
		<p x="-10.991211" y="12.764072" z="-346.972656" w="0.952906"/>
	</T>
	<T>
		<p x="-21.072266" y="12.550452" z="-362.431641" w="0.919407"/>
	</T>
	<T>
		<p x="-28.162109" y="12.537351" z="-375.342773" w="0.961943"/>
	</T>
	<T>
		<p x="-37.084961" y="12.542477" z="-391.071289" w="1.045436"/>
	</T>
	<T>
		<p x="-20.442383" y="12.507239" z="-377.476563" w="1.087497"/>
	</T>
	<T>
		<p x="-30.973633" y="12.528152" z="-386.636719" w="0.909363"/>
	</T>
	<T>
		<p x="51.375" y="9.580076" z="-117" w="1.033788"/>
	</T>
	<T>
		<p x="45.699219" y="11.399584" z="-119.069336" w="1.076677"/>
	</T>
	<T>
		<p x="43.737305" y="12.101242" z="-131.411133" w="0.947953"/>
	</T>
	<T>
		<p x="40.663086" y="12.085322" z="-124.604492" w="0.993806"/>
	</T>
	<T>
		<p x="38.585938" y="12.537283" z="-135.038086" w="0.927815"/>
	</T>
	<T>
		<p x="42.963867" y="12.498964" z="-143.199219" w="0.919779"/>
	</T>
	<T>
		<p x="45.263672" y="13.275727" z="-65.97168" w="1.082008"/>
	</T>
	<T>
		<p x="36.03418" y="13.275727" z="-68.237305" w="0.951342"/>
	</T>
	<T>
		<p x="42.783203" y="13.275727" z="-72.672852" w="0.926915"/>
	</T>
	<T>
		<p x="38.469727" y="13.275728" z="-80.692383" w="0.901854"/>
	</T>
	<T>
		<p x="13.310547" y="13.914638" z="-155.373047" w="1.067044"/>
	</T>
	<T>
		<p x="12.886719" y="13.701351" z="-146.94043" w="0.931394"/>
	</T>
	<T>
		<p x="19.004883" y="13.307155" z="-145.693359" w="1.888088"/>
	</T>
	<T>
		<p x="16.352539" y="13.243601" z="-137.930664" w="0.963067"/>
	</T>
	<T>
		<p x="10.723633" y="13.571938" z="-137.861328" w="0.993949"/>
	</T>
	<T>
		<p x="8.890625" y="13.396165" z="-127.828125" w="0.912135"/>
	</T>
	<T>
		<p x="14.558594" y="13.098236" z="-129.054688" w="0.907945"/>
	</T>
	<T>
		<p x="19.930664" y="12.962973" z="-123.09668" w="1.08902"/>
	</T>
	<T>
		<p x="11.382813" y="13.094581" z="-120.517578" w="0.950716"/>
	</T>
	<T>
		<p x="4.401367" y="13.267554" z="-113.944336" w="1.038295"/>
	</T>
	<T>
		<p x="9.475586" y="13.12736" z="-111.335938" w="0.99601"/>
	</T>
	<T>
		<p x="16.162109" y="13.027823" z="-113.500977" w="0.993085"/>
	</T>
	<T>
		<p x="2.959961" y="13.235546" z="-105.726563" w="1.728087"/>
	</T>
	<T>
		<p x="-5.294922" y="13.275727" z="-98.950195" w="1.069965"/>
	</T>
	<T>
		<p x="17.37793" y="13.130188" z="-136.045898" w="0.963015"/>
	</T>
	<T>
		<p x="-389.460938" y="14.620726" z="-115.713867" w="1.051522"/>
	</T>
	<T>
		<p x="-380.920898" y="12.984468" z="-140.368164" w="1.072462"/>
	</T>
	<T>
		<p x="-394.700195" y="13.536995" z="-118.223633" w="1.01619"/>
	</T>
	<T>
		<p x="-405.90625" y="12.708418" z="-107.036133" w="0.98603"/>
	</T>
	<T>
		<p x="-387.615234" y="15.438888" z="-109.978516" w="0.954271"/>
	</T>
	<T>
		<p x="-383.69043" y="14.135494" z="-127.828125" w="1.061307"/>
	</T>
	<T>
		<p x="-394.77832" y="12.845929" z="-125.763672" w="0.970335"/>
	</T>
	<T>
		<p x="-410.076172" y="11.555367" z="-112.262695" w="0.959489"/>
	</T>
	<T>
		<p x="-394.936523" y="14.567115" z="-106.342773" w="0.919022"/>
	</T>
	<T>
		<p x="-410.210938" y="12.582919" z="-100.594727" w="1.037741"/>
	</T>
	<T>
		<p x="-424.489258" y="10.337699" z="-99.5625" w="0.921964"/>
	</T>
	<T>
		<p x="-413.289063" y="11.408174" z="-108.049805" w="1.006801"/>
	</T>
	<T>
		<p x="-418.762695" y="11.558418" z="-96.416016" w="1.028201"/>
	</T>
	<T>
		<p x="-419.547852" y="10.686862" z="-104.674805" w="0.98893"/>
	</T>
	<T>
		<p x="-404.211914" y="11.534831" z="-123.165039" w="0.940012"/>
	</T>
	<T>
		<p x="-400.509766" y="12.433769" z="-119.913086" w="1.095821"/>
	</T>
	<T>
		<p x="-389.279297" y="12.104403" z="-138.913086" w="1.077338"/>
	</T>
	<T>
		<p x="-393" y="12.52631" z="-131.463867" w="1.098932"/>
	</T>
	<T>
		<p x="-384.980469" y="10.515952" z="-156.72168" w="0.92357"/>
	</T>
	<T>
		<p x="-383.584961" y="11.709654" z="-148.214844" w="1.58808"/>
	</T>
	<T>
		<p x="-381.814453" y="11.644747" z="-150.625" w="0.993962"/>
	</T>
	<T>
		<p x="-386.337891" y="6.61995" z="-187.853516" w="1.050996"/>
	</T>
	<T>
		<p x="-380.786133" y="5.764025" z="-200.860352" w="1.04838"/>
	</T>
	<T>
		<p x="-378.822266" y="7.325717" z="-189.876953" w="1.072132"/>
	</T>
	<T>
		<p x="-390.015625" y="5.262849" z="-195.319336" w="0.946199"/>
	</T>
	<T>
		<p x="-385.99707" y="7.634518" z="-179.733398" w="1.078242"/>
	</T>
	<T>
		<p x="-380.677734" y="8.912885" z="-174.655273" w="1.050963"/>
	</T>
	<T>
		<p x="-397.348633" y="5.197752" z="-188.132813" w="1.075222"/>
	</T>
	<T>
		<p x="-395.641602" y="6.656006" z="-177.744141" w="0.923303"/>
	</T>
	<T>
		<p x="-380.889648" y="9.758176" z="-167.367188" w="1.058963"/>
	</T>
	<T>
		<p x="-404.355469" y="5.694178" z="-176.597656" w="0.911146"/>
	</T>
	<T>
		<p x="-408.755859" y="7.224515" z="-159.167969" w="0.92913"/>
	</T>
	<T>
		<p x="-404.464844" y="9.095078" z="-148.056641" w="0.91365"/>
	</T>
	<T>
		<p x="-410.53418" y="7.937861" z="-151.331055" w="0.923666"/>
	</T>
	<T>
		<p x="-412.152344" y="8.105121" z="-146.835938" w="1.81885"/>
	</T>
	<T>
		<p x="-413.121094" y="9.050114" z="-134.568359" w="1.00931"/>
	</T>
	<T>
		<p x="-418.75" y="8.044302" z="-135.501953" w="0.986402"/>
	</T>
	<T>
		<p x="-414.511719" y="7.848001" z="-145.400391" w="0.976217"/>
	</T>
	<T>
		<p x="-421.381836" y="6.712444" z="-145.517578" w="1.0525"/>
	</T>
	<T>
		<p x="-416.681641" y="6.634627" z="-154.939453" w="0.93661"/>
	</T>
	<T>
		<p x="-148.040039" y="1.209716" z="-490.96582" w="0.931123"/>
	</T>
	<T>
		<p x="-165.621094" y="0.510316" z="-480.640625" w="1.042238"/>
	</T>
	<T>
		<p x="-157.30957" y="0.915705" z="-487.444336" w="1.035284"/>
	</T>
	<T>
		<p x="-156.762695" y="0.456255" z="-475.006836" w="1.060998"/>
	</T>
	<T>
		<p x="-178.963867" y="0.253951" z="-480.525391" w="0.936502"/>
	</T>
	<T>
		<p x="-176.43457" y="1.071708" z="-494.054688" w="1.095247"/>
	</T>
	<T>
		<p x="-161.529297" y="1.385298" z="-498.522461" w="1.081994"/>
	</T>
	<T>
		<p x="-129.00293" y="1.250026" z="-483.267578" w="0.979107"/>
	</T>
	<T>
		<p x="-176.362305" y="0.477758" z="-485.650391" w="1.000301"/>
	</T>
	<T>
		<p x="-190.987305" y="1.003414" z="-492.533203" w="1.005435"/>
	</T>
	<T>
		<p x="-142.932617" y="1.471442" z="-496.167969" w="0.999657"/>
	</T>
	<T>
		<p x="-89.03125" y="0.773451" z="-416.310547" w="1.075148"/>
	</T>
	<T>
		<p x="-99.833984" y="0.569816" z="-401.613281" w="1.047923"/>
	</T>
	<T>
		<p x="-103.067383" y="1.04595" z="-381.543945" w="1.066702"/>
	</T>
	<T>
		<p x="-106.513672" y="1.146766" z="-368.561523" w="1.036647"/>
	</T>
	<T>
		<p x="-109.738281" y="0.817865" z="-376.294922" w="0.990962"/>
	</T>
	<T>
		<p x="-99.265625" y="0.962468" z="-391.984375" w="0.958189"/>
	</T>
	<T>
		<p x="-87.358398" y="1.014299" z="-407.335938" w="1.007059"/>
	</T>
	<T>
		<p x="-90.243164" y="1.234696" z="-385.859375" w="1.000129"/>
	</T>
	<T>
		<p x="-96.025391" y="1.323118" z="-370.375977" w="0.911322"/>
	</T>
	<T>
		<p x="-94.298828" y="1.204926" z="-359.827148" w="1.074879"/>
	</T>
	<T>
		<p x="-78.923828" y="1.736936" z="-352.514648" w="0.96725"/>
	</T>
	<T>
		<p x="-67.740234" y="1.990716" z="-346.244141" w="0.981056"/>
	</T>
	<T>
		<p x="-76.270508" y="1.768814" z="-364.936523" w="1.733911"/>
	</T>
	<T>
		<p x="-83.621094" y="1.701959" z="-359.239258" w="0.959246"/>
	</T>
	<T>
		<p x="-87.162109" y="1.066812" z="-353.681641" w="0.985197"/>
	</T>
	<T>
		<p x="-72.371094" y="1.963352" z="-355.550781" w="1.042514"/>
	</T>
	<T>
		<p x="-63.586914" y="2.184383" z="-351.349609" w="1.029394"/>
	</T>
	<T>
		<p x="-73.783203" y="1.779413" z="-367.802734" w="0.962727"/>
	</T>
	<T>
		<p x="-66.958984" y="1.977192" z="-362.506836" w="1.025941"/>
	</T>
	<T>
		<p x="-83.044922" y="1.515098" z="-374.671875" w="1.064079"/>
	</T>
	<T>
		<p x="-88.004883" y="1.524692" z="-366.55957" w="0.916145"/>
	</T>
	<T>
		<p x="-104.236328" y="0.691316" z="-363.34082" w="0.940655"/>
	</T>
	<T>
		<p x="-99.6875" y="1.166071" z="-377.191406" w="0.982229"/>
	</T>
	<T>
		<p x="-94.084961" y="1.272122" z="-377.236328" w="1.053076"/>
	</T>
	<T>
		<p x="-107.880859" y="0.545648" z="-387.189453" w="0.996329"/>
	</T>
	<T>
		<p x="-104" y="0.617138" z="-392.516602" w="1.068794"/>
	</T>
	<T>
		<p x="-92.219727" y="1.05496" z="-396.947266" w="1.070739"/>
	</T>
	<T>
		<p x="-80.524414" y="1.441318" z="-384.169922" w="0.90864"/>
	</T>
	<T>
		<p x="-73.317383" y="1.633035" z="-379.914063" w="0.962189"/>
	</T>
	<T>
		<p x="-82.025391" y="1.211362" z="-399.880859" w="0.988324"/>
	</T>
	<T>
		<p x="-83.44043" y="1.044868" z="-410.769531" w="0.919199"/>
	</T>
	<T>
		<p x="-84.205078" y="1.275323" z="-391.655273" w="0.980715"/>
	</T>
	<T>
		<p x="-76.279297" y="1.462007" z="-388.859375" w="1.005894"/>
	</T>
	<T>
		<p x="361.550781" y="4.235976" z="-435.65625" w="0.94399"/>
	</T>
	<T>
		<p x="353.368164" y="4.037897" z="-434.882813" w="1.092228"/>
	</T>
	<T>
		<p x="348.641602" y="3.772831" z="-432.335938" w="0.980957"/>
	</T>
	<T>
		<p x="357.233398" y="5.700181" z="-447.21875" w="1.731839"/>
	</T>
	<T>
		<p x="376.113281" y="5.280912" z="-445.043945" w="0.950668"/>
	</T>
	<T>
		<p x="383.34375" y="5.859818" z="-449.904297" w="0.955397"/>
	</T>
	<T>
		<p x="358.943359" y="5.515565" z="-445.618164" w="0.940428"/>
	</T>
	<T>
		<p x="364.075195" y="4.706794" z="-440.213867" w="1.075308"/>
	</T>
	<T>
		<p x="368.630859" y="5.161386" z="-444.952148" w="1.084837"/>
	</T>
	<T>
		<p x="367.217773" y="6.173444" z="-452.816406" w="1.074222"/>
	</T>
	<T>
		<p x="350.040039" y="4.892064" z="-441.793945" w="0.975529"/>
	</T>
	<T>
		<p x="379.233398" y="6.824621" z="-460.464844" w="0.972594"/>
	</T>
	<T>
		<p x="375.573242" y="6.206087" z="-454.652344" w="0.909864"/>
	</T>
	<T>
		<p x="395.833008" y="6.674775" z="-456.394531" w="0.987732"/>
	</T>
	<T>
		<p x="400.993164" y="7.085051" z="-447.69043" w="0.971448"/>
	</T>
	<T>
		<p x="391.19043" y="6.18629" z="-447.786133" w="0.976776"/>
	</T>
	<T>
		<p x="386.042969" y="7.031192" z="-461.554688" w="1.064858"/>
	</T>
	<T>
		<p x="399.210938" y="7.424032" z="-463.594727" w="0.940046"/>
	</T>
	<T>
		<p x="414.392578" y="7.893457" z="-457.941406" w="0.950907"/>
	</T>
	<T>
		<p x="429.859375" y="7.63086" z="-453.223633" w="0.991614"/>
	</T>
	<T>
		<p x="418.742188" y="9.643082" z="-441.038086" w="1.062302"/>
	</T>
	<T>
		<p x="403.345703" y="9.914913" z="-437.243164" w="0.965379"/>
	</T>
	<T>
		<p x="389.560547" y="8.166718" z="-434.689453" w="1.097251"/>
	</T>
	<T>
		<p x="376.619141" y="6.614137" z="-431.913086" w="1.066296"/>
	</T>
	<T>
		<p x="372.192383" y="7.843521" z="-415.572266" w="0.905314"/>
	</T>
	<T>
		<p x="367.259766" y="9.659831" z="-401.405273" w="1.762799"/>
	</T>
	<T>
		<p x="356.626953" y="8.359965" z="-412.595703" w="1.064561"/>
	</T>
	<T>
		<p x="361.612305" y="6.124175" z="-421.385742" w="1.002861"/>
	</T>
	<T>
		<p x="366.373047" y="5.548414" z="-425.991211" w="1.823701"/>
	</T>
	<T>
		<p x="369.881836" y="6.305421" z="-424.916992" w="1.008728"/>
	</T>
	<T>
		<p x="366.817383" y="7.227778" z="-413.603516" w="0.915931"/>
	</T>
	<T>
		<p x="371.874023" y="9.307452" z="-402.94043" w="0.972793"/>
	</T>
	<T>
		<p x="380.109375" y="10.449816" z="-405.686523" w="1.076746"/>
	</T>
	<T>
		<p x="386.90332" y="11.057959" z="-410.728516" w="1.840011"/>
	</T>
	<T>
		<p x="392.105469" y="12.649858" z="-405.234375" w="1.036271"/>
	</T>
	<T>
		<p x="392.668945" y="14.301196" z="-390.78418" w="0.909877"/>
	</T>
	<T>
		<p x="389.072266" y="14.659316" z="-384.036133" w="1.054028"/>
	</T>
	<T>
		<p x="379.048828" y="13.271449" z="-380.672852" w="0.914064"/>
	</T>
	<T>
		<p x="373.411133" y="13.04348" z="-381.949219" w="1.064522"/>
	</T>
	<T>
		<p x="362.167969" y="12.812248" z="-388.140625" w="0.988543"/>
	</T>
	<T>
		<p x="359.921875" y="11.451004" z="-395.865234" w="1.004954"/>
	</T>
	<T>
		<p x="380.094727" y="12.057388" z="-392.310547" w="1.731674"/>
	</T>
	<T>
		<p x="382.547852" y="11.913221" z="-397.15332" w="1.093499"/>
	</T>
	<T>
		<p x="375.667969" y="11.064338" z="-393.982422" w="0.967712"/>
	</T>
	<T>
		<p x="366.071289" y="11.400624" z="-393.351563" w="1.026663"/>
	</T>
	<T>
		<p x="379.928711" y="13.002863" z="-384.211914" w="1.093345"/>
	</T>
	<T>
		<p x="390.132813" y="13.460993" z="-395.56543" w="0.932653"/>
	</T>
	<T>
		<p x="397.857422" y="13.572107" z="-397.214844" w="0.915055"/>
	</T>
	<T>
		<p x="357.261719" y="10.105269" z="-403.699219" w="1.081818"/>
	</T>
	<T>
		<p x="347.607422" y="10.513164" z="-404.946289" w="1.074845"/>
	</T>
	<T>
		<p x="343.842773" y="4.716094" z="-428.261719" w="0.902491"/>
	</T>
	<T>
		<p x="333.236328" y="5.091084" z="-425.621094" w="1.718817"/>
	</T>
	<T>
		<p x="356.477539" y="6.07069" z="-423.424805" w="1.000357"/>
	</T>
	<T>
		<p x="345.449219" y="6.993542" z="-419.108398" w="0.971667"/>
	</T>
	<T>
		<p x="340.416992" y="8.216075" z="-413.888672" w="1.096196"/>
	</T>
	<T>
		<p x="328.24707" y="7.140189" z="-416.227539" w="1.00748"/>
	</T>
	<T>
		<p x="333.288086" y="6.056525" z="-421.666016" w="0.915942"/>
	</T>
	<T>
		<p x="314.75293" y="4.804158" z="-423.175781" w="1.021417"/>
	</T>
	<T>
		<p x="307.080078" y="5.474011" z="-418.920898" w="0.953247"/>
	</T>
	<T>
		<p x="298.355469" y="5.122254" z="-418.591797" w="0.930279"/>
	</T>
	<T>
		<p x="292.486328" y="7.967686" z="-405.246094" w="0.928632"/>
	</T>
	<T>
		<p x="312.532227" y="7.662839" z="-411" w="1.790347"/>
	</T>
	<T>
		<p x="319.816406" y="8.17074" z="-410.341797" w="0.92572"/>
	</T>
	<T>
		<p x="336.458984" y="10.761989" z="-402.962891" w="1.085257"/>
	</T>
	<T>
		<p x="345.277344" y="12.92832" z="-395.029297" w="0.931187"/>
	</T>
	<T>
		<p x="351.84668" y="14.138059" z="-386.236328" w="1.064454"/>
	</T>
	<T>
		<p x="368.385742" y="16.363359" z="-367.828125" w="1.04649"/>
	</T>
	<T>
		<p x="379.939453" y="16.410429" z="-362.405273" w="1.089074"/>
	</T>
	<T>
		<p x="374.250977" y="15.303123" z="-370.423828" w="1.029376"/>
	</T>
	<T>
		<p x="359.453125" y="15.56576" z="-375.775391" w="0.910401"/>
	</T>
	<T>
		<p x="348.250977" y="15.711458" z="-380.089844" w="1.027104"/>
	</T>
	<T>
		<p x="338.038086" y="14.254172" z="-388.929688" w="1.045337"/>
	</T>
	<T>
		<p x="332.925781" y="12.089763" z="-396.816406" w="1.039014"/>
	</T>
	<T>
		<p x="320.828125" y="10.290353" z="-401.834961" w="0.977718"/>
	</T>
	<T>
		<p x="312.317383" y="10.720567" z="-398.104492" w="0.98999"/>
	</T>
	<T>
		<p x="325.647461" y="13.434897" z="-389.654297" w="1.002024"/>
	</T>
	<T>
		<p x="308.439453" y="8.030701" z="-408.587891" w="1.004777"/>
	</T>
	<T>
		<p x="297.407227" y="6.384647" z="-413.044922" w="1.056287"/>
	</T>
	<T>
		<p x="300.598633" y="9.105006" z="-402.277344" w="1.001352"/>
	</T>
	<T>
		<p x="291.908203" y="9.835713" z="-397.225586" w="0.994959"/>
	</T>
	<T>
		<p x="283.235352" y="8.321415" z="-401.660156" w="1.055806"/>
	</T>
	<T>
		<p x="279.307617" y="9.6733" z="-395.061523" w="0.909508"/>
	</T>
	<T>
		<p x="286.307617" y="6.310668" z="-410.847656" w="0.900376"/>
	</T>
	<T>
		<p x="291.186523" y="4.013149" z="-421.654297" w="0.961499"/>
	</T>
	<T>
		<p x="277.587891" y="7.923622" z="-414.325195" w="1.011549"/>
	</T>
	<T>
		<p x="273.005859" y="9.077411" z="-402.97168" w="1.033691"/>
	</T>
	<T>
		<p x="262.563477" y="8.082074" z="-392.566406" w="0.938474"/>
	</T>
	<T>
		<p x="207.368164" y="5.030308" z="-358.352539" w="1.027743"/>
	</T>
	<T>
		<p x="208.582031" y="5.009507" z="-364.02832" w="0.997756"/>
	</T>
	<T>
		<p x="214.65332" y="4.853697" z="-368.058594" w="0.975389"/>
	</T>
	<T>
		<p x="213.619141" y="5.013613" z="-348.776367" w="0.989468"/>
	</T>
	<T>
		<p x="220.438477" y="4.888084" z="-360.484375" w="1.083363"/>
	</T>
	<T>
		<p x="225.283203" y="4.656727" z="-371.396484" w="1.682389"/>
	</T>
	<T>
		<p x="224.44043" y="4.678229" z="-370.310547" w="1.032724"/>
	</T>
	<T>
		<p x="213.755859" y="5.043924" z="-353.681641" w="1.067223"/>
	</T>
	<T>
		<p x="229.523438" y="4.568373" z="-374.09668" w="0.968619"/>
	</T>
	<T>
		<p x="230.894531" y="4.473997" z="-383.519531" w="1.869632"/>
	</T>
	<T>
		<p x="218.793945" y="4.739114" z="-374.648438" w="0.929506"/>
	</T>
	<T>
		<p x="232.864258" y="4.436708" z="-383.701172" w="0.902854"/>
	</T>
	<T>
		<p x="243.932617" y="4.257353" z="-381.510742" w="1.024133"/>
	</T>
	<T>
		<p x="233.59082" y="4.631936" z="-361.443359" w="0.983411"/>
	</T>
	<T>
		<p x="224.584961" y="5.063051" z="-345.105469" w="0.985661"/>
	</T>
	<T>
		<p x="229.550781" y="4.821019" z="-356.703125" w="1.062434"/>
	</T>
	<T>
		<p x="238.043945" y="4.450788" z="-371.141602" w="0.963164"/>
	</T>
	<T>
		<p x="238.449219" y="4.357203" z="-381.422852" w="1.068475"/>
	</T>
	<T>
		<p x="234.475586" y="4.354109" z="-389.410156" w="0.979875"/>
	</T>
	<T>
		<p x="245.044922" y="4.723553" z="-393.480469" w="1.004978"/>
	</T>
	<T>
		<p x="248.816406" y="4.298766" z="-367.681641" w="1.006073"/>
	</T>
	<T>
		<p x="254.527344" y="5.870251" z="-384.391602" w="0.915293"/>
	</T>
	<T>
		<p x="257.753906" y="7.402408" z="-395.921875" w="1.007394"/>
	</T>
	<T>
		<p x="244.649414" y="5.170951" z="-400.199219" w="1.02442"/>
	</T>
	<T>
		<p x="252.926758" y="7.148124" z="-404.767578" w="1.067952"/>
	</T>
	<T>
		<p x="264.704102" y="8.926105" z="-407.060547" w="0.987323"/>
	</T>
	<T>
		<p x="269.139648" y="9.566254" z="-396.249023" w="1.025682"/>
	</T>
	<T>
		<p x="271.526367" y="8.190766" z="-413.296875" w="0.920271"/>
	</T>
	<T>
		<p x="251.599609" y="5.943708" z="-392.670898" w="1.001374"/>
	</T>
	<T>
		<p x="399.916992" y="32.059704" z="-162.689453" w="0.911618"/>
	</T>
	<T>
		<p x="409.351563" y="31.9639" z="-155.53418" w="0.941544"/>
	</T>
	<T>
		<p x="407.445313" y="31.520266" z="-162.15918" w="1.061653"/>
	</T>
	<T>
		<p x="404.203125" y="31.046776" z="-170.283203" w="1.036822"/>
	</T>
	<T>
		<p x="405.922852" y="30.048481" z="-180.950195" w="1.097081"/>
	</T>
	<T>
		<p x="410.46875" y="29.035557" z="-188.827148" w="0.990485"/>
	</T>
	<T>
		<p x="414.317383" y="27.812305" z="-201.076172" w="0.922242"/>
	</T>
	<T>
		<p x="418.491211" y="27.712658" z="-195.639648" w="1.083827"/>
	</T>
	<T>
		<p x="418.589844" y="28.574404" z="-185.394531" w="0.983321"/>
	</T>
	<T>
		<p x="411.730469" y="29.789768" z="-177.780273" w="0.950651"/>
	</T>
	<T>
		<p x="414.170898" y="30.311436" z="-169.816406" w="1.074002"/>
	</T>
	<T>
		<p x="421.254883" y="29.636425" z="-171.189453" w="1.09516"/>
	</T>
	<T>
		<p x="417.975586" y="30.975159" z="-159.074219" w="0.976031"/>
	</T>
	<T>
		<p x="418.40918" y="32.058247" z="-146.581055" w="1.068609"/>
	</T>
	<T>
		<p x="426.710938" y="31.816582" z="-142.044922" w="0.925211"/>
	</T>
	<T>
		<p x="416.009766" y="31.767294" z="-151.926758" w="1.065172"/>
	</T>
	<T>
		<p x="425.549805" y="31.087797" z="-151.209961" w="0.954211"/>
	</T>
	<T>
		<p x="424.03418" y="30.176624" z="-162.723633" w="1.011915"/>
	</T>
	<T>
		<p x="429.967773" y="30.479523" z="-156.908203" w="0.954561"/>
	</T>
	<T>
		<p x="431.52832" y="31.396996" z="-144.290039" w="1.084134"/>
	</T>
</Trees>

