<?xml version="1.0" encoding="UTF-8"?>
<definition is_island="true" tile_type="2" is_purchasable="false" purchase_cost="0" sea_floor_height="-6">
	<meshes>
		<mesh id="mesh0" parent_id="" purchase_interactable_id="" seasonal_flags="0" file_name="meshes/mainland/mega_island_10_3.mesh">
			<transform 00="1" 01="0" 02="0" 03="0" 10="0" 11="1" 12="0" 13="0" 20="0" 21="0" 22="1" 23="0" 30="0" 31="0" 32="0" 33="1"/>
		</mesh>
		<mesh id="base_02" parent_id="" purchase_interactable_id="" seasonal_flags="0" file_name="meshes/mainland_assets/bascule_bridge_base.mesh">
			<transform 00="0.866025" 01="0" 02="-0.5" 03="0" 10="0" 11="1" 12="0" 13="0" 20="0.5" 21="0" 22="0.866025" 23="0" 30="363.130005" 31="15.47" 32="308.350006" 33="1"/>
		</mesh>
		<mesh id="base_01" parent_id="" purchase_interactable_id="" seasonal_flags="0" file_name="meshes/mainland_assets/bascule_bridge_base.mesh">
			<transform 00="-0.866025" 01="0" 02="0.5" 03="0" 10="0" 11="1" 12="0" 13="0" 20="-0.5" 21="0" 22="-0.866025" 23="0" 30="408.554382" 31="15.473963" 32="387.050629" 33="1"/>
		</mesh>
		<mesh id="bridge_arm_01" parent_id="" purchase_interactable_id="" seasonal_flags="0" file_name="meshes/mainland_assets/bascule_bridge_arm.mesh">
			<transform 00="-0.866025" 01="0" 02="0.5" 03="0" 10="0" 11="1" 12="0" 13="0" 20="-0.5" 21="0" 22="-0.866025" 23="0" 30="408.554382" 31="15.473963" 32="387.050629" 33="1"/>
		</mesh>
		<mesh id="bridge_arm_02" parent_id="" purchase_interactable_id="" seasonal_flags="0" file_name="meshes/mainland_assets/bascule_bridge_arm.mesh">
			<transform 00="0.866025" 01="0" 02="-0.5" 03="0" 10="0" 11="1" 12="0" 13="0" 20="0.5" 21="0" 22="0.866025" 23="0" 30="363.130005" 31="15.47" 32="308.350006" 33="1"/>
		</mesh>
	</meshes>
	<physics_objects/>
	<physics_meshes>
		<physics_mesh id="physics_mesh0" parent_id="" purchase_interactable_id="" seasonal_flags="0" file_name="meshes/mainland/mega_island_10_3.phys">
			<transform 00="1" 01="0" 02="0" 03="0" 10="0" 11="1" 12="0" 13="0" 20="0" 21="0" 22="1" 23="0" 30="0" 31="0" 32="0" 33="1"/>
		</physics_mesh>
		<physics_mesh id="base_02_phys" parent_id="" purchase_interactable_id="" seasonal_flags="0" file_name="meshes/mainland_assets/bascule_bridge_base_phys.phys">
			<transform 00="0.866025" 01="0" 02="-0.5" 03="0" 10="0" 11="1" 12="0" 13="0" 20="0.5" 21="0" 22="0.866025" 23="0" 30="363.130005" 31="15.47" 32="308.350006" 33="1"/>
		</physics_mesh>
		<physics_mesh id="bridge_arm_02_phys" parent_id="bridge_arm_02" purchase_interactable_id="" seasonal_flags="0" file_name="meshes/mainland_assets/bascule_bridge_arm_phys.phys">
			<transform 00="0.866025" 01="0" 02="-0.5" 03="0" 10="0" 11="1" 12="0" 13="0" 20="0.5" 21="0" 22="0.866025" 23="0" 30="363.130005" 31="15.47" 32="308.350006" 33="1"/>
		</physics_mesh>
		<physics_mesh id="bridge_arm_01_phys" parent_id="bridge_arm_01" purchase_interactable_id="" seasonal_flags="0" file_name="meshes/mainland_assets/bascule_bridge_arm_phys.phys">
			<transform 00="-0.866025" 01="0" 02="0.5" 03="0" 10="0" 11="1" 12="0" 13="0" 20="-0.5" 21="0" 22="-0.866025" 23="0" 30="408.554382" 31="15.473963" 32="387.050629" 33="1"/>
		</physics_mesh>
		<physics_mesh id="base_01_phys" parent_id="" purchase_interactable_id="" seasonal_flags="0" file_name="meshes/mainland_assets/bascule_bridge_base_phys.phys">
			<transform 00="-0.866025" 01="0" 02="0.5" 03="0" 10="0" 11="1" 12="0" 13="0" 20="-0.5" 21="0" 22="-0.866025" 23="0" 30="408.554382" 31="15.473963" 32="387.050629" 33="1"/>
		</physics_mesh>
	</physics_meshes>
	<physics_dynamics/>
	<lights_omni>
		<light id="omni0" parent_id="" purchase_interactable_id="" seasonal_flags="0" radius="2" is_render_halo="true">
			<transform 00="1" 01="0" 02="0" 03="0" 10="0" 11="1" 12="0" 13="0" 20="0" 21="0" 22="1" 23="0" 30="367.114288" 31="18.459591" 32="300.07431" 33="1"/>
			<color x="0.8" y="0.8" z="0.6"/>
		</light>
		<light id="omni1" parent_id="" purchase_interactable_id="" seasonal_flags="0" radius="4" is_render_halo="true">
			<transform 00="1" 01="0" 02="0" 03="0" 10="0" 11="1" 12="0" 13="0" 20="0" 21="0" 22="1" 23="0" 30="369.096008" 31="18.839516" 32="299.767639" 33="1"/>
			<color x="1" y="1" z="0.8"/>
		</light>
		<light id="omni2" parent_id="" purchase_interactable_id="" seasonal_flags="0" radius="4" is_render_halo="true">
			<transform 00="1" 01="0" 02="0" 03="0" 10="0" 11="1" 12="0" 13="0" 20="0" 21="0" 22="1" 23="0" 30="402.58316" 31="18.839516" 32="395.628967" 33="1"/>
			<color x="1" y="1" z="0.8"/>
		</light>
		<light id="omni3" parent_id="" purchase_interactable_id="" seasonal_flags="0" radius="2" is_render_halo="true">
			<transform 00="1" 01="0" 02="0" 03="0" 10="0" 11="1" 12="0" 13="0" 20="0" 21="0" 22="1" 23="0" 30="404.569" 31="18.461796" 32="395.326111" 33="1"/>
			<color x="0.8" y="0.8" z="0.6"/>
		</light>
		<light id="omni4" parent_id="" purchase_interactable_id="" seasonal_flags="0" radius="0.5" is_render_halo="true">
			<transform 00="0.870477" 01="0" 02="-0.492208" 03="0" 10="0" 11="1" 12="0" 13="0" 20="0.492208" 21="0" 22="0.870477" 23="0" 30="416.961945" 31="13.047161" 32="384.736664" 33="1"/>
			<color x="1" y="1" z="1"/>
		</light>
		<light id="omni5" parent_id="" purchase_interactable_id="" seasonal_flags="0" radius="0.5" is_render_halo="true">
			<transform 00="0.870477" 01="0" 02="-0.492208" 03="0" 10="0" 11="1" 12="0" 13="0" 20="0.492208" 21="0" 22="0.870477" 23="0" 30="421.952484" 31="13.042631" 32="393.394775" 33="1"/>
			<color x="1" y="1" z="1"/>
		</light>
		<light id="omni6" parent_id="" purchase_interactable_id="" seasonal_flags="0" radius="0.5" is_render_halo="true">
			<transform 00="0.870477" 01="0" 02="-0.492208" 03="0" 10="0" 11="1" 12="0" 13="0" 20="0.492208" 21="0" 22="0.870477" 23="0" 30="402.336304" 31="8.888308" 32="393.196472" 33="1"/>
			<color x="1" y="1" z="1"/>
		</light>
		<light id="omni7" parent_id="" purchase_interactable_id="" seasonal_flags="0" radius="0.5" is_render_halo="true">
			<transform 00="0.870477" 01="0" 02="-0.492208" 03="0" 10="0" 11="1" 12="0" 13="0" 20="0.492208" 21="0" 22="0.870477" 23="0" 30="407.325531" 31="8.867029" 32="401.845306" 33="1"/>
			<color x="1" y="1" z="1"/>
		</light>
		<light id="omni8" parent_id="" purchase_interactable_id="" seasonal_flags="0" radius="0.5" is_render_halo="true">
			<transform 00="0.870477" 01="0" 02="-0.492208" 03="0" 10="0" 11="1" 12="0" 13="0" 20="0.492208" 21="0" 22="0.870477" 23="0" 30="354.707825" 31="13.049576" 32="310.667603" 33="1"/>
			<color x="1" y="1" z="1"/>
		</light>
		<light id="omni9" parent_id="" purchase_interactable_id="" seasonal_flags="0" radius="0.5" is_render_halo="true">
			<transform 00="0.870477" 01="0" 02="-0.492208" 03="0" 10="0" 11="1" 12="0" 13="0" 20="0.492208" 21="0" 22="0.870477" 23="0" 30="349.691681" 31="13.049576" 32="302.029968" 33="1"/>
			<color x="1" y="1" z="1"/>
		</light>
		<light id="omni10" parent_id="" purchase_interactable_id="" seasonal_flags="0" radius="0.5" is_render_halo="true">
			<transform 00="0.870477" 01="0" 02="-0.492208" 03="0" 10="0" 11="1" 12="0" 13="0" 20="0.492208" 21="0" 22="0.870477" 23="0" 30="364.381958" 31="8.884224" 32="293.53006" 33="1"/>
			<color x="1" y="1" z="1"/>
		</light>
		<light id="omni11" parent_id="" purchase_interactable_id="" seasonal_flags="0" radius="0.5" is_render_halo="true">
			<transform 00="0.870477" 01="0" 02="-0.492208" 03="0" 10="0" 11="1" 12="0" 13="0" 20="0.492208" 21="0" 22="0.870477" 23="0" 30="369.358887" 31="8.888575" 32="302.220978" 33="1"/>
			<color x="1" y="1" z="1"/>
		</light>
		<light id="omni12" parent_id="bridge_arm_02" purchase_interactable_id="" seasonal_flags="0" radius="2" is_render_halo="true">
			<transform 00="0.870477" 01="0" 02="-0.492208" 03="0" 10="0" 11="1" 12="0" 13="0" 20="0.492208" 21="0" 22="0.870477" 23="0" 30="389.715515" 31="14.143767" 32="343.591827" 33="1"/>
			<color x="3" y="0" z="0"/>
		</light>
		<light id="omni13" parent_id="bridge_arm_01" purchase_interactable_id="" seasonal_flags="0" radius="2" is_render_halo="true">
			<transform 00="0.870477" 01="0" 02="-0.492208" 03="0" 10="0" 11="1" 12="0" 13="0" 20="0.492208" 21="0" 22="0.870477" 23="0" 30="391.312714" 31="14.143767" 32="346.416473" 33="1"/>
			<color x="3" y="0" z="0"/>
		</light>
		<light id="omni14" parent_id="bridge_arm_01" purchase_interactable_id="" seasonal_flags="0" radius="2" is_render_halo="true">
			<transform 00="0.870477" 01="0" 02="-0.492208" 03="0" 10="0" 11="1" 12="0" 13="0" 20="0.492208" 21="0" 22="0.870477" 23="0" 30="381.955414" 31="14.143767" 32="351.815765" 33="1"/>
			<color x="3" y="0" z="0"/>
		</light>
		<light id="omni15" parent_id="bridge_arm_02" purchase_interactable_id="" seasonal_flags="0" radius="2" is_render_halo="true">
			<transform 00="0.870477" 01="0" 02="-0.492208" 03="0" 10="0" 11="1" 12="0" 13="0" 20="0.492208" 21="0" 22="0.870477" 23="0" 30="380.358887" 31="14.143767" 32="348.992279" 33="1"/>
			<color x="3" y="0" z="0"/>
		</light>
		<light id="omni16" parent_id="" purchase_interactable_id="" seasonal_flags="0" radius="2" is_render_halo="true">
			<transform 00="0.870477" 01="0" 02="-0.492208" 03="0" 10="0" 11="1" 12="0" 13="0" 20="0.492208" 21="0" 22="0.870477" 23="0" 30="362.566284" 31="6.805155" 32="315.228729" 33="1"/>
			<color x="1" y="1" z="1"/>
		</light>
		<light id="omni17" parent_id="" purchase_interactable_id="" seasonal_flags="0" radius="2" is_render_halo="true">
			<transform 00="0.870477" 01="0" 02="-0.492208" 03="0" 10="0" 11="1" 12="0" 13="0" 20="0.492208" 21="0" 22="0.870477" 23="0" 30="366.043823" 31="6.805155" 32="313.243011" 33="1"/>
			<color x="1" y="1" z="1"/>
		</light>
		<light id="omni18" parent_id="" purchase_interactable_id="" seasonal_flags="0" radius="2" is_render_halo="true">
			<transform 00="0.870477" 01="0" 02="-0.492208" 03="0" 10="0" 11="1" 12="0" 13="0" 20="0.492208" 21="0" 22="0.870477" 23="0" 30="369.501709" 31="6.805155" 32="311.230072" 33="1"/>
			<color x="1" y="1" z="1"/>
		</light>
		<light id="omni19" parent_id="" purchase_interactable_id="" seasonal_flags="0" radius="2" is_render_halo="true">
			<transform 00="0.870477" 01="0" 02="-0.492208" 03="0" 10="0" 11="1" 12="0" 13="0" 20="0.492208" 21="0" 22="0.870477" 23="0" 30="409.110657" 31="6.821904" 32="380.160675" 33="1"/>
			<color x="1" y="1" z="1"/>
		</light>
		<light id="omni20" parent_id="" purchase_interactable_id="" seasonal_flags="0" radius="2" is_render_halo="true">
			<transform 00="0.870477" 01="0" 02="-0.492208" 03="0" 10="0" 11="1" 12="0" 13="0" 20="0.492208" 21="0" 22="0.870477" 23="0" 30="405.650116" 31="6.821904" 32="382.182129" 33="1"/>
			<color x="1" y="1" z="1"/>
		</light>
		<light id="omni21" parent_id="" purchase_interactable_id="" seasonal_flags="0" radius="2" is_render_halo="true">
			<transform 00="0.870477" 01="0" 02="-0.492208" 03="0" 10="0" 11="1" 12="0" 13="0" 20="0.492208" 21="0" 22="0.870477" 23="0" 30="402.186707" 31="6.821904" 32="384.176788" 33="1"/>
			<color x="1" y="1" z="1"/>
		</light>
	</lights_omni>
	<lights_spot>
		<light id="spot0" parent_id="" purchase_interactable_id="" seasonal_flags="0" range="8" fov="0.349066" texture="graphics/ies/ies_default.txtr">
			<transform 00="0.493158" 01="-0" 02="0.86994" 03="0" 10="-0.869414" 11="0.034767" 12="0.49286" 13="0" 20="-0.030245" 21="-0.999396" 22="0.017146" 23="0" 30="354.764252" 31="13.107437" 32="310.63559" 33="1"/>
			<color x="1" y="1" z="1"/>
		</light>
		<light id="spot1" parent_id="" purchase_interactable_id="" seasonal_flags="0" range="8" fov="0.349066" texture="graphics/ies/ies_default.txtr">
			<transform 00="0.493158" 01="-0" 02="0.86994" 03="0" 10="-0.869414" 11="0.034767" 12="0.49286" 13="0" 20="-0.030245" 21="-0.999396" 22="0.017146" 23="0" 30="349.830231" 31="13.107437" 32="301.931915" 33="1"/>
			<color x="1" y="1" z="1"/>
		</light>
		<light id="spot2" parent_id="" purchase_interactable_id="" seasonal_flags="0" range="8" fov="0.349066" texture="graphics/ies/ies_default.txtr">
			<transform 00="-0.493158" 01="-0" 02="-0.86994" 03="0" 10="0.869414" 11="0.034767" 12="-0.49286" 13="0" 20="0.030245" 21="-0.999396" 22="-0.017146" 23="0" 30="364.316132" 31="8.904187" 32="293.568115" 33="1"/>
			<color x="1" y="1" z="1"/>
		</light>
		<light id="spot3" parent_id="" purchase_interactable_id="" seasonal_flags="0" range="8" fov="0.349066" texture="graphics/ies/ies_default.txtr">
			<transform 00="-0.493158" 01="-0" 02="-0.86994" 03="0" 10="0.869414" 11="0.034767" 12="-0.49286" 13="0" 20="0.030245" 21="-0.999396" 22="-0.017146" 23="0" 30="369.254822" 31="8.904187" 32="302.28009" 33="1"/>
			<color x="1" y="1" z="1"/>
		</light>
		<light id="spot4" parent_id="" purchase_interactable_id="" seasonal_flags="0" range="8" fov="0.349066" texture="graphics/ies/ies_default.txtr">
			<transform 00="-0.493158" 01="-0" 02="-0.86994" 03="0" 10="0.869414" 11="0.034767" 12="-0.49286" 13="0" 20="0.030245" 21="-0.999396" 22="-0.017146" 23="0" 30="416.929382" 31="13.092092" 32="384.747253" 33="1"/>
			<color x="1" y="1" z="1"/>
		</light>
		<light id="spot5" parent_id="" purchase_interactable_id="" seasonal_flags="0" range="8" fov="0.349066" texture="graphics/ies/ies_default.txtr">
			<transform 00="-0.493158" 01="-0" 02="-0.86994" 03="0" 10="0.869414" 11="0.034767" 12="-0.49286" 13="0" 20="0.030245" 21="-0.999396" 22="-0.017146" 23="0" 30="421.862457" 31="13.092092" 32="393.44931" 33="1"/>
			<color x="1" y="1" z="1"/>
		</light>
		<light id="spot6" parent_id="" purchase_interactable_id="" seasonal_flags="0" range="8" fov="0.349066" texture="graphics/ies/ies_default.txtr">
			<transform 00="0.493158" 01="-0" 02="0.86994" 03="0" 10="-0.869414" 11="0.034767" 12="0.49286" 13="0" 20="-0.030245" 21="-0.999396" 22="0.017146" 23="0" 30="407.387268" 31="8.875908" 32="401.819977" 33="1"/>
			<color x="1" y="1" z="1"/>
		</light>
		<light id="spot7" parent_id="" purchase_interactable_id="" seasonal_flags="0" range="8" fov="0.349066" texture="graphics/ies/ies_default.txtr">
			<transform 00="0.493158" 01="-0" 02="0.86994" 03="0" 10="-0.869414" 11="0.034767" 12="0.49286" 13="0" 20="-0.030245" 21="-0.999396" 22="0.017146" 23="0" 30="402.377106" 31="8.913056" 32="393.158844" 33="1"/>
			<color x="1" y="1" z="1"/>
		</light>
	</lights_spot>
	<lights_tube>
		<light id="tube0" parent_id="" purchase_interactable_id="" seasonal_flags="0" length="4" radius="4">
			<transform 00="0.486496" 01="0.008453" 02="0.873642" 03="0" 10="0.402845" 11="0.885142" 12="-0.232892" 13="0" 20="-0.775266" 21="0.465244" 22="0.427213" 23="0" 30="414.508667" 31="19.752747" 32="391.002777" 33="1"/>
			<color x="1" y="1" z="1"/>
		</light>
		<light id="tube1" parent_id="" purchase_interactable_id="" seasonal_flags="0" length="4" radius="4">
			<transform 00="0.486496" 01="0.008453" 02="0.873642" 03="0" 10="0.402845" 11="0.885142" 12="-0.232892" 13="0" 20="-0.775266" 21="0.465244" 22="0.427213" 23="0" 30="422.949127" 31="19.802937" 32="405.23822" 33="1"/>
			<color x="1" y="1" z="1"/>
		</light>
		<light id="tube2" parent_id="" purchase_interactable_id="" seasonal_flags="0" length="4" radius="4">
			<transform 00="0.486496" 01="0.008453" 02="0.873642" 03="0" 10="0.396957" 11="0.888644" 12="-0.229647" 13="0" 20="-0.778298" 21="0.458521" 22="0.428966" 23="0" 30="434.050812" 31="19.906666" 32="424.772034" 33="1"/>
			<color x="1" y="1" z="1"/>
		</light>
		<light id="tube3" parent_id="" purchase_interactable_id="" seasonal_flags="0" length="4" radius="4">
			<transform 00="0.486496" 01="0.008453" 02="0.873642" 03="0" 10="0.396957" 11="0.888644" 12="-0.229647" 13="0" 20="-0.778298" 21="0.458521" 22="0.428966" 23="0" 30="445.309875" 31="19.940289" 32="444.230316" 33="1"/>
			<color x="1" y="1" z="1"/>
		</light>
		<light id="tube4" parent_id="" purchase_interactable_id="" seasonal_flags="0" length="4" radius="4">
			<transform 00="0.486496" 01="0.008453" 02="0.873642" 03="0" 10="0.396957" 11="0.888644" 12="-0.229647" 13="0" 20="-0.778298" 21="0.458521" 22="0.428966" 23="0" 30="456.625275" 31="19.836069" 32="463.69281" 33="1"/>
			<color x="1" y="1" z="1"/>
		</light>
		<light id="tube5" parent_id="" purchase_interactable_id="" seasonal_flags="0" length="4" radius="4">
			<transform 00="0.493987" 01="-0.009781" 02="0.869415" 03="0" 10="-0.388" 11="0.892373" 12="0.230494" 13="0" 20="-0.778096" 21="-0.451193" 22="0.437026" 23="0" 30="450.717468" 31="19.943863" 32="467.087646" 33="1"/>
			<color x="1" y="1" z="1"/>
		</light>
		<light id="tube6" parent_id="" purchase_interactable_id="" seasonal_flags="0" length="4" radius="4">
			<transform 00="0.493987" 01="-0.009781" 02="0.869415" 03="0" 10="-0.388" 11="0.892373" 12="0.230494" 13="0" 20="-0.778096" 21="-0.451193" 22="0.437026" 23="0" 30="439.645142" 31="19.85141" 32="447.499084" 33="1"/>
			<color x="1" y="1" z="1"/>
		</light>
		<light id="tube7" parent_id="" purchase_interactable_id="" seasonal_flags="0" length="4" radius="4">
			<transform 00="0.493987" 01="-0.009781" 02="0.869415" 03="0" 10="-0.388" 11="0.892373" 12="0.230494" 13="0" 20="-0.778096" 21="-0.451193" 22="0.437026" 23="0" 30="428.246063" 31="19.931211" 32="428.076263" 33="1"/>
			<color x="1" y="1" z="1"/>
		</light>
		<light id="tube8" parent_id="" purchase_interactable_id="" seasonal_flags="0" length="4" radius="4">
			<transform 00="0.493987" 01="-0.009781" 02="0.869415" 03="0" 10="-0.388" 11="0.892373" 12="0.230494" 13="0" 20="-0.778096" 21="-0.451193" 22="0.437026" 23="0" 30="417.104736" 31="19.765646" 32="408.639343" 33="1"/>
			<color x="1" y="1" z="1"/>
		</light>
		<light id="tube9" parent_id="" purchase_interactable_id="" seasonal_flags="0" length="4" radius="4">
			<transform 00="0.493987" 01="-0.009781" 02="0.869415" 03="0" 10="-0.388" 11="0.892373" 12="0.230494" 13="0" 20="-0.778096" 21="-0.451193" 22="0.437026" 23="0" 30="408.878296" 31="19.567402" 32="394.343323" 33="1"/>
			<color x="1" y="1" z="1"/>
		</light>
		<light id="tube10" parent_id="" purchase_interactable_id="" seasonal_flags="0" length="4" radius="4">
			<transform 00="0.486496" 01="0.008453" 02="0.873642" 03="0" 10="0.402845" 11="0.885142" 12="-0.232892" 13="0" 20="-0.775266" 21="0.465244" 22="0.427213" 23="0" 30="362.683624" 31="19.519222" 32="301.15152" 33="1"/>
			<color x="1" y="1" z="1"/>
		</light>
		<light id="tube11" parent_id="" purchase_interactable_id="" seasonal_flags="0" length="4" radius="4">
			<transform 00="0.486496" 01="0.008453" 02="0.873642" 03="0" 10="0.402845" 11="0.885142" 12="-0.232892" 13="0" 20="-0.775266" 21="0.465244" 22="0.427213" 23="0" 30="354.558899" 31="19.744812" 32="286.800232" 33="1"/>
			<color x="1" y="1" z="1"/>
		</light>
		<light id="tube12" parent_id="" purchase_interactable_id="" seasonal_flags="0" length="4" radius="4">
			<transform 00="0.486496" 01="0.008453" 02="0.873642" 03="0" 10="0.402845" 11="0.885142" 12="-0.232892" 13="0" 20="-0.775266" 21="0.465244" 22="0.427213" 23="0" 30="343.352264" 31="19.878433" 32="267.235962" 33="1"/>
			<color x="1" y="1" z="1"/>
		</light>
		<light id="tube13" parent_id="" purchase_interactable_id="" seasonal_flags="0" length="4" radius="4">
			<transform 00="0.482292" 01="-0.000726" 02="0.87601" 03="0" 10="0.407868" 11="0.885182" 12="-0.22382" 13="0" 20="-0.775266" 21="0.465244" 22="0.427213" 23="0" 30="331.991272" 31="19.919535" 32="247.941467" 33="1"/>
			<color x="1" y="1" z="1"/>
		</light>
		<light id="tube14" parent_id="" purchase_interactable_id="" seasonal_flags="0" length="4" radius="4">
			<transform 00="0.482292" 01="-0.000726" 02="0.87601" 03="0" 10="0.407868" 11="0.885182" 12="-0.22382" 13="0" 20="-0.775266" 21="0.465244" 22="0.427213" 23="0" 30="320.84613" 31="19.964947" 32="228.229111" 33="1"/>
			<color x="1" y="1" z="1"/>
		</light>
		<light id="tube15" parent_id="" purchase_interactable_id="" seasonal_flags="0" length="4" radius="4">
			<transform 00="0.493987" 01="-0.009781" 02="0.869415" 03="0" 10="-0.388" 11="0.892373" 12="0.230494" 13="0" 20="-0.778096" 21="-0.451193" 22="0.437026" 23="0" 30="357.02887" 31="19.897545" 32="304.464905" 33="1"/>
			<color x="1" y="1" z="1"/>
		</light>
		<light id="tube16" parent_id="" purchase_interactable_id="" seasonal_flags="0" length="4" radius="4">
			<transform 00="0.493987" 01="-0.009781" 02="0.869415" 03="0" 10="-0.388" 11="0.892373" 12="0.230494" 13="0" 20="-0.778096" 21="-0.451193" 22="0.437026" 23="0" 30="348.483276" 31="19.797482" 32="290.327332" 33="1"/>
			<color x="1" y="1" z="1"/>
		</light>
		<light id="tube17" parent_id="" purchase_interactable_id="" seasonal_flags="0" length="4" radius="4">
			<transform 00="0.493987" 01="-0.009781" 02="0.869415" 03="0" 10="-0.388" 11="0.892373" 12="0.230494" 13="0" 20="-0.778096" 21="-0.451193" 22="0.437026" 23="0" 30="337.492096" 31="19.931702" 32="270.736023" 33="1"/>
			<color x="1" y="1" z="1"/>
		</light>
		<light id="tube18" parent_id="" purchase_interactable_id="" seasonal_flags="0" length="4" radius="4">
			<transform 00="0.493987" 01="-0.009781" 02="0.869415" 03="0" 10="-0.388" 11="0.892373" 12="0.230494" 13="0" 20="-0.778096" 21="-0.451193" 22="0.437026" 23="0" 30="326.151611" 31="19.836424" 32="251.366241" 33="1"/>
			<color x="1" y="1" z="1"/>
		</light>
		<light id="tube19" parent_id="" purchase_interactable_id="" seasonal_flags="0" length="4" radius="4">
			<transform 00="0.493987" 01="-0.009781" 02="0.869415" 03="0" 10="-0.388" 11="0.892373" 12="0.230494" 13="0" 20="-0.778096" 21="-0.451193" 22="0.437026" 23="0" 30="314.883118" 31="20.080704" 32="231.88826" 33="1"/>
			<color x="1" y="1" z="1"/>
		</light>
	</lights_tube>
	<screens/>
	<edit_areas/>
	<interactables>
		<interactable id="bridge_02_interact" parent_id="" purchase_interactable_id="" seasonal_flags="0" target_object_id="bridge_logic" label="Bridge" use_case="0" interact_type="0" is_purchased="false" is_ignore_purchased="false">
			<transform 00="0.866025" 01="0" 02="-0.5" 03="0" 10="0" 11="1" 12="0" 13="0" 20="0.5" 21="0" 22="0.866025" 23="0" 30="369.895996" 31="17.622532" 32="301.062561" 33="1"/>
			<size x="0.840015" y="0.889099" z="0.541708"/>
		</interactable>
		<interactable id="bridge_01_interact" parent_id="" purchase_interactable_id="" seasonal_flags="0" target_object_id="bridge_logic" label="Bridge" use_case="0" interact_type="0" is_purchased="false" is_ignore_purchased="false">
			<transform 00="0.866025" 01="0" 02="-0.5" 03="0" 10="0" 11="1" 12="0" 13="0" 20="0.5" 21="0" 22="0.866025" 23="0" 30="401.770355" 31="17.622532" 32="394.301422" 33="1"/>
			<size x="0.840015" y="0.889099" z="0.541708"/>
		</interactable>
	</interactables>
	<door_logic_nodes>
		<logic id="bridge_01_logic" parent_id="" purchase_interactable_id="" seasonal_flags="0" target_a="bridge_arm_01_closed" target_b="bridge_arm_01_open" target_movable="bridge_arm_01" target_triggered="" pos_index="0" pos_factor="0" anim_duration="1200" anim_delay="0" anim_delay_back="0" is_on="false" behavior="0">
			<transform 00="0.870138" 01="0" 02="-0.492808" 03="0" 10="0" 11="1" 12="0" 13="0" 20="0.492808" 21="0" 22="0.870138" 23="0" 30="402.358246" 31="17.622532" 32="393.692078" 33="1"/>
		</logic>
		<logic id="bridge_02_logic" parent_id="" purchase_interactable_id="" seasonal_flags="0" target_a="bridge_arm_02_closed" target_b="bridge_arm_02_open" target_movable="bridge_arm_02" target_triggered="" pos_index="0" pos_factor="0" anim_duration="1200" anim_delay="0" anim_delay_back="0" is_on="false" behavior="0">
			<transform 00="-0.857888" 01="0" 02="0.513836" 03="0" 10="0" 11="1" 12="0" 13="0" 20="-0.513836" 21="0" 22="-0.857888" 23="0" 30="369.383179" 31="17.622532" 32="301.802185" 33="1"/>
		</logic>
	</door_logic_nodes>
	<light_logic_nodes/>
	<rotation_logic_nodes/>
	<hangar_door_logic_nodes>
		<logic id="bridge_logic" parent_id="" purchase_interactable_id="" seasonal_flags="0" target_id_0="bridge_01_logic" target_id_1="bridge_02_logic" target_id_2="" target_id_3="" target_id_4="" target_id_5="" target_id_6="" target_id_7="" trigger_on_delay="0" cooldown_time="0">
			<transform 00="0.876055" 01="0" 02="-0.482211" 03="0" 10="0" 11="1" 12="0" 13="0" 20="0.482211" 21="0" 22="0.876055" 23="0" 30="402.358246" 31="18.114092" 32="393.692078" 33="1"/>
		</logic>
	</hangar_door_logic_nodes>
	<audio_logic_nodes/>
	<tile_markers>
		<markers id="bridge_arm_01_closed" parent_id="" purchase_interactable_id="" seasonal_flags="0" marker_type="8" is_in_ocean="false" string_data="" icon="1">
			<transform 00="-0.866025" 01="0" 02="0.5" 03="0" 10="0" 11="1" 12="0" 13="0" 20="-0.5" 21="0" 22="-0.866025" 23="0" 30="408.554382" 31="15.473963" 32="387.050629" 33="1"/>
		</markers>
		<markers id="bridge_arm_01_open" parent_id="" purchase_interactable_id="" seasonal_flags="0" marker_type="8" is_in_ocean="false" string_data="" icon="1">
			<transform 00="-0.866025" 01="0" 02="0.5" 03="0" 10="0.392202" 11="0.620251" 12="0.679314" 13="0" 20="-0.310125" 21="0.784404" 22="-0.537153" 23="0" 30="408.554382" 31="15.473963" 32="387.050629" 33="1"/>
		</markers>
		<markers id="bridge_arm_02_closed" parent_id="" purchase_interactable_id="" seasonal_flags="0" marker_type="8" is_in_ocean="false" string_data="" icon="1">
			<transform 00="0.866025" 01="0" 02="-0.5" 03="0" 10="0" 11="1" 12="0" 13="0" 20="0.5" 21="0" 22="0.866025" 23="0" 30="363.130005" 31="15.47" 32="308.350006" 33="1"/>
		</markers>
		<markers id="bridge_arm_02_open" parent_id="" purchase_interactable_id="" seasonal_flags="0" marker_type="8" is_in_ocean="false" string_data="" icon="1">
			<transform 00="0.866025" 01="0" 02="-0.5" 03="0" 10="-0.395667" 11="0.611385" 12="-0.685314" 13="0" 20="0.305693" 21="0.791333" 22="0.529475" 23="0" 30="363.129242" 31="15.47" 32="308.348663" 33="1"/>
		</markers>
	</tile_markers>
	<mission_zones/>
	<dynamic_markers/>
	<ladders>
		<ladder id="ladder_0" parent_id="" purchase_interactable_id="" seasonal_flags="0" height="12">
			<transform 00="0.5" 01="0" 02="0.866025" 03="0" 10="0" 11="1" 12="0" 13="0" 20="-0.866025" 21="0" 22="0.5" 23="0" 30="398.778442" 31="1.497031" 32="392.793732" 33="1"/>
		</ladder>
		<ladder id="ladder_1" parent_id="" purchase_interactable_id="" seasonal_flags="0" height="12">
			<transform 00="-0.5" 01="0" 02="-0.866025" 03="0" 10="0" 11="1" 12="0" 13="0" 20="0.866025" 21="0" 22="-0.5" 23="0" 30="372.915924" 31="1.497627" 32="302.594421" 33="1"/>
		</ladder>
	</ladders>
	<perches>
		<perch id="perch0" parent_id="" purchase_interactable_id="" seasonal_flags="0" type="0">
			<transform 00="1" 01="0" 02="0" 03="0" 10="0" 11="1" 12="0" 13="0" 20="0" 21="0" 22="1" 23="0" 30="-249.029083" 31="38.993217" 32="-381.86554" 33="1"/>
		</perch>
		<perch id="perch1" parent_id="" purchase_interactable_id="" seasonal_flags="0" type="0">
			<transform 00="1" 01="0" 02="0" 03="0" 10="0" 11="1" 12="0" 13="0" 20="0" 21="0" 22="1" 23="0" 30="-259.759949" 31="48.182858" 32="-364.238342" 33="1"/>
		</perch>
		<perch id="perch2" parent_id="" purchase_interactable_id="" seasonal_flags="0" type="0">
			<transform 00="1" 01="0" 02="0" 03="0" 10="0" 11="1" 12="0" 13="0" 20="0" 21="0" 22="1" 23="0" 30="-236.960556" 31="37.519405" 32="-355.962219" 33="1"/>
		</perch>
		<perch id="perch3" parent_id="" purchase_interactable_id="" seasonal_flags="0" type="0">
			<transform 00="1" 01="0" 02="0" 03="0" 10="0" 11="1" 12="0" 13="0" 20="0" 21="0" 22="1" 23="0" 30="-270.47702" 31="80.331749" 32="-252.133789" 33="1"/>
		</perch>
		<perch id="perch4" parent_id="" purchase_interactable_id="" seasonal_flags="0" type="0">
			<transform 00="1" 01="0" 02="0" 03="0" 10="0" 11="1" 12="0" 13="0" 20="0" 21="0" 22="1" 23="0" 30="-273.234161" 31="80.685799" 32="-244.564056" 33="1"/>
		</perch>
		<perch id="perch5" parent_id="" purchase_interactable_id="" seasonal_flags="0" type="0">
			<transform 00="1" 01="0" 02="0" 03="0" 10="0" 11="1" 12="0" 13="0" 20="0" 21="0" 22="1" 23="0" 30="-443.099884" 31="131.097824" 32="174.970581" 33="1"/>
		</perch>
		<perch id="perch6" parent_id="" purchase_interactable_id="" seasonal_flags="0" type="0">
			<transform 00="1" 01="0" 02="0" 03="0" 10="0" 11="1" 12="0" 13="0" 20="0" 21="0" 22="1" 23="0" 30="373.479279" 31="14.542048" 32="303.773285" 33="1"/>
		</perch>
		<perch id="perch7" parent_id="" purchase_interactable_id="" seasonal_flags="0" type="0">
			<transform 00="1" 01="0" 02="0" 03="0" 10="0" 11="1" 12="0" 13="0" 20="0" 21="0" 22="1" 23="0" 30="372.138489" 31="14.542048" 32="304.543274" 33="1"/>
		</perch>
		<perch id="perch8" parent_id="" purchase_interactable_id="" seasonal_flags="0" type="0">
			<transform 00="1" 01="0" 02="0" 03="0" 10="0" 11="1" 12="0" 13="0" 20="0" 21="0" 22="1" 23="0" 30="372.013123" 31="14.210466" 32="307.812958" 33="1"/>
		</perch>
		<perch id="perch9" parent_id="" purchase_interactable_id="" seasonal_flags="0" type="0">
			<transform 00="1" 01="0" 02="0" 03="0" 10="0" 11="1" 12="0" 13="0" 20="0" 21="0" 22="1" 23="0" 30="358.841705" 31="14.210466" 32="287.955078" 33="1"/>
		</perch>
		<perch id="perch10" parent_id="" purchase_interactable_id="" seasonal_flags="0" type="0">
			<transform 00="1" 01="0" 02="0" 03="0" 10="0" 11="1" 12="0" 13="0" 20="0" 21="0" 22="1" 23="0" 30="366.867249" 31="17.750267" 32="292.302765" 33="1"/>
		</perch>
		<perch id="perch11" parent_id="" purchase_interactable_id="" seasonal_flags="0" type="0">
			<transform 00="1" 01="0" 02="0" 03="0" 10="0" 11="1" 12="0" 13="0" 20="0" 21="0" 22="1" 23="0" 30="371.801147" 31="19.112591" 32="300.855255" 33="1"/>
		</perch>
		<perch id="perch12" parent_id="" purchase_interactable_id="" seasonal_flags="0" type="0">
			<transform 00="1" 01="0" 02="0" 03="0" 10="0" 11="1" 12="0" 13="0" 20="0" 21="0" 22="1" 23="0" 30="356.921783" 31="21.075462" 32="304.566101" 33="1"/>
		</perch>
		<perch id="perch13" parent_id="" purchase_interactable_id="" seasonal_flags="0" type="0">
			<transform 00="1" 01="0" 02="0" 03="0" 10="0" 11="1" 12="0" 13="0" 20="0" 21="0" 22="1" 23="0" 30="347.041107" 31="14.21" 32="296.437195" 33="1"/>
		</perch>
		<perch id="perch14" parent_id="" purchase_interactable_id="" seasonal_flags="0" type="0">
			<transform 00="1" 01="0" 02="0" 03="0" 10="0" 11="1" 12="0" 13="0" 20="0" 21="0" 22="1" 23="0" 30="360.256378" 31="14.21" 32="316.342865" 33="1"/>
		</perch>
	</perches>
	<fires/>
	<train_tracks/>
	<iceberg_markers/>
</definition>

